pyama/__init__.py
pyama/constants.py
pyama/download.py
pyama/prompt.py
pyama/static/style.css
pyama/templates/base.html
pyama/templates/models.html
pyama/templates/prompts.html
pyama-0.1.0.dist-info/entry_points.txt
pyama-0.1.0.dist-info/WHEEL
pyama-0.1.0.dist-info/METADATA
pyama-0.1.0.dist-info/RECORD
